file_query_tool/__init__.py
file_query_tool/cli.py
file_query_tool/gitignore_parser.py
file_query_tool/grammar.py
file_query_tool/main.py
file_query_tool-0.1.13.dist-info/METADATA
file_query_tool-0.1.13.dist-info/WHEEL
file_query_tool-0.1.13.dist-info/entry_points.txt
file_query_tool-0.1.13.dist-info/top_level.txt
file_query_tool-0.1.13.dist-info/RECORD
